{
  "_fv": 24,
  "_type": "recipe",
  "definition": {
    "recipeType": "Crafting",
    "xpReward": 0.0,
    "cookingTime": 200,
    "recipeRetstackSize": 1,
    "group": "",
    "recipeShapeless": false,
    "recipeSlots": [
      {
        "value": ""
      },
      {
        "value": "CUSTOM:BouteilledO2"
      },
      {
        "value": ""
      },
      {
        "value": "Items.LEATHER"
      },
      {
        "value": "Items.LEATHER"
      },
      {
        "value": "Items.LEATHER"
      },
      {
        "value": ""
      },
      {
        "value": "CUSTOM:BouteilledO2"
      },
      {
        "value": ""
      }
    ],
    "recipeReturnStack": {
      "value": "CUSTOM:Combi_de_plongeeArmor.body"
    },
    "name": "combi_de_plongee_armor_body_recipe",
    "namespace": "mod"
  }
}